{"data":[{"id":"cmlszmh5u0002gosbbsisfcq4","completed":false,"score":null,"updatedAt":"2026-02-19T04:55:27.330Z","lesson":{"id":"cmlrtkpu400016zsbfm1c2vy1","title":"Introduction to Offline Web Apps","slug":"intro-to-offline-apps","order":1},"user":{"id":"cmlszmh520001gosbee4lqvy7","name":"Enrolled Student","email":"enrolled@orbit.edu"}},{"id":"cmlrwi4lv000cq9sbtl5wdztm","completed":false,"score":null,"updatedAt":"2026-02-18T10:40:19.411Z","lesson":{"id":"cmlrtkpu400016zsbfm1c2vy1","title":"Introduction to Offline Web Apps","slug":"intro-to-offline-apps","order":1},"user":{"id":"cmlrwi4ls000bq9sbc9r3iwu7","name":"Benchmark User 2","email":"benchmark-2-1771411219400@orbit.edu"}},{"id":"cmlrwi4l40001q9sbuhidefw3","completed":false,"score":null,"updatedAt":"2026-02-18T10:40:19.384Z","lesson":{"id":"cmlrtkpu400016zsbfm1c2vy1","title":"Introduction to Offline Web Apps","slug":"intro-to-offline-apps","order":1},"user":{"id":"cmlrwi4kq0000q9sbhl7em2w3","name":"Benchmark Test User","email":"benchmark-1771411219312@orbit.edu"}},{"id":"cmlrwdsjx001g5isbh3ckrjw0","completed":false,"score":null,"updatedAt":"2026-02-18T10:36:57.165Z","lesson":{"id":"cmlrtkpu400016zsbfm1c2vy1","title":"Introduction to Offline Web Apps","slug":"intro-to-offline-apps","order":1},"user":{"id":"cmlrwdsjt001f5isb0ct8jl8n","name":"Benchmark User 2","email":"benchmark-2-1771411017153@orbit.edu"}},{"id":"cmlrwdsj400155isbcddwo86z","completed":false,"score":null,"updatedAt":"2026-02-18T10:36:57.136Z","lesson":{"id":"cmlrtkpu400016zsbfm1c2vy1","title":"Introduction to Offline Web Apps","slug":"intro-to-offline-apps","order":1},"user":{"id":"cmlrwdsiz00145isbcujy1kl0","name":"Benchmark Test User","email":"benchmark-1771411017089@orbit.edu"}},{"id":"cmlrwcs8m000o5isbdil1k9ww","completed":false,"score":null,"updatedAt":"2026-02-18T10:36:10.102Z","lesson":{"id":"cmlrtkpu400016zsbfm1c2vy1","title":"Introduction to Offline Web Apps","slug":"intro-to-offline-apps","order":1},"user":{"id":"cmlrwcs8i000n5isbbqifho6g","name":"Bob Smith","email":"bob.smith@orbit.edu"}},{"id":"cmlrwcje2000c5isbtskh1p91","completed":false,"score":null,"updatedAt":"2026-02-18T10:35:58.634Z","lesson":{"id":"cmlrtkpu400016zsbfm1c2vy1","title":"Introduction to Offline Web Apps","slug":"intro-to-offline-apps","order":1},"user":{"id":"cmlrwcjdz000b5isbypa8bpxo","name":"Bob Smith","email":"bob@orbit.edu"}},{"id":"cmlrwceq800015isbbfcp801b","completed":false,"score":null,"updatedAt":"2026-02-18T10:35:52.592Z","lesson":{"id":"cmlrtkpu400016zsbfm1c2vy1","title":"Introduction to Offline Web Apps","slug":"intro-to-offline-apps","order":1},"user":{"id":"cmlrwcepo00005isbuxh5szih","name":"Alice Johnson","email":"alice@orbit.edu"}},{"id":"cmlrvcv2c000ca9sbeanwylp2","completed":false,"score":null,"updatedAt":"2026-02-18T10:08:14.148Z","lesson":{"id":"cmlrtkpu400016zsbfm1c2vy1","title":"Introduction to Offline Web Apps","slug":"intro-to-offline-apps","order":1},"user":{"id":"cmlrvcv27000ba9sbo1neovv4","name":"Benchmark User 2","email":"benchmark-2-1771409294135@orbit.edu"}},{"id":"cmlrvcv1g0001a9sbyzzf0lgz","completed":false,"score":null,"updatedAt":"2026-02-18T10:08:14.116Z","lesson":{"id":"cmlrtkpu400016zsbfm1c2vy1","title":"Introduction to Offline Web Apps","slug":"intro-to-offline-apps","order":1},"user":{"id":"cmlrvcv0v0000a9sbz2uayjx8","name":"Benchmark Test User","email":"benchmark-1771409293589@orbit.edu"}}],"pagination":{"page":1,"limit":10,"total":10,"totalPages":1,"hasMore":false}}